AUTHORS.rst
CONTRIBUTING.rst
LICENSE
MANIFEST.in
README.md
requirements.txt
setup.cfg
setup.py
versioneer.py
demi/__init__.py
demi/_version.py
demi/demi.py
demi.egg-info/PKG-INFO
demi.egg-info/SOURCES.txt
demi.egg-info/dependency_links.txt
demi.egg-info/entry_points.txt
demi.egg-info/top_level.txt
demi/bin/__init__.py
demi/bin/help.py
demi/bin/import.py
demi/bin/main.py
demi/tests/__init__.py
demi/tests/cls_ab.py
demi/tests/conftest.py
demi/tests/test_simple.py
docs/Makefile
docs/make.bat
docs/source/conf.py
docs/source/index.rst