Metadata-Version: 2.1
Name: demi
Version: 0.0.0
Summary: de-multiple-inheritance; squash class inheritance
Home-page: https://github.com/klauer/demi
Author: K Lauer
License: BSD
Platform: UNKNOWN
Classifier: Development Status :: 2 - Pre-Alpha
Classifier: Natural Language :: English
Classifier: Programming Language :: Python :: 3
License-File: LICENSE
License-File: AUTHORS.rst
